stateful_data_processor/__init__.py
stateful_data_processor/_version.py
stateful_data_processor/file_rw.py
stateful_data_processor/processor.py
stateful_data_processor-3.4.1.dist-info/licenses/AUTHORS.rst
stateful_data_processor-3.4.1.dist-info/licenses/LICENSE.txt
stateful_data_processor-3.4.1.dist-info/METADATA
stateful_data_processor-3.4.1.dist-info/WHEEL
stateful_data_processor-3.4.1.dist-info/top_level.txt
stateful_data_processor-3.4.1.dist-info/RECORD
