Metadata-Version: 2.4
Name: stateful-data-processor
Version: 3.4.1
Summary: Resumable, checkpointed item processing with graceful interrupts.
Author: Doru Irimescu
License: The MIT License (MIT)
Project-URL: Documentation, https://github.com/doruirimescu/stateful-data-processor/
Project-URL: Source, https://github.com/doruirimescu/stateful-data-processor/
Classifier: License :: OSI Approved :: MIT License
Classifier: Programming Language :: Python :: 3
Classifier: Programming Language :: Python :: 3 :: Only
Classifier: Programming Language :: Python :: 3.9
Classifier: Programming Language :: Python :: 3.10
Classifier: Programming Language :: Python :: 3.11
Classifier: Programming Language :: Python :: 3.12
Classifier: Programming Language :: Python :: 3.13
Requires-Python: >=3.9
License-File: LICENSE.txt
License-File: AUTHORS.rst
Provides-Extra: testing
Requires-Dist: setuptools; extra == "testing"
Requires-Dist: pytest>=7; extra == "testing"
Requires-Dist: pytest-cov; extra == "testing"
Dynamic: license-file
